[
  { "id": "fc_ssc_001", "front": "What is the HCF of 24 and 36?", "back": "12. The highest common factor is found by listing prime factors: 24 = 2³×3, 36 = 2²×3². HCF = 2²×3 = 12." },
  { "id": "fc_ssc_002", "front": "State the Pythagorean theorem.", "back": "In a right-angled triangle, the square of the hypotenuse equals the sum of the squares of the other two sides: a² + b² = c²." },
  { "id": "fc_ssc_003", "front": "What is the formula for the area of a triangle?", "back": "Area = (1/2) × base × height." },
  { "id": "fc_ssc_004", "front": "What is sin 30°?", "back": "sin 30° = 1/2." },
  { "id": "fc_ssc_005", "front": "What is cos 60°?", "back": "cos 60° = 1/2." },
  { "id": "fc_ssc_006", "front": "What is the sum of the first n natural numbers?", "back": "Sum = n(n+1)/2. For n=10: 10×11/2 = 55." },
  { "id": "fc_ssc_007", "front": "What is the total surface area formula for a cube?", "back": "Total Surface Area = 6a², where a is the side length." },
  { "id": "fc_ssc_008", "front": "What is the volume formula for a cone?", "back": "Volume = (1/3)πr²h, where r is radius and h is height." },
  { "id": "fc_ssc_009", "front": "What quadrant does the point (3, -4) lie in?", "back": "Quadrant IV, because the x-coordinate is positive and the y-coordinate is negative." },
  { "id": "fc_ssc_010", "front": "What is the slope of a horizontal line parallel to the x-axis?", "back": "0, because the vertical change (rise) is zero." },
  { "id": "fc_ssc_011", "front": "What is the formula for the volume of a sphere?", "back": "Volume = (4/3)πr³, where r is the radius." },
  { "id": "fc_ssc_012", "front": "What is the angle in a semi-circle?", "back": "90° (a right angle)." },
  { "id": "fc_ssc_013", "front": "Define a rational number.", "back": "A number that can be expressed in the form p/q where p and q are integers and q ≠ 0." },
  { "id": "fc_ssc_014", "front": "What is the probability of a certain event?", "back": "1 (or 100%)." },
  { "id": "fc_ssc_015", "front": "What is the formula for the distance between point (x, y) and origin?", "back": "Distance = √(x² + y²)." },
  { "id": "fc_ssc_016", "front": "Where does photosynthesis occur in plant cells?", "back": "In the chloroplasts, which contain chlorophyll." },
  { "id": "fc_ssc_017", "front": "State Newton's First Law of Motion.", "back": "An object at rest stays at rest and an object in motion continues in motion with the same speed and direction unless acted upon by an external force. Also called the Law of Inertia." },
  { "id": "fc_ssc_018", "front": "What is the SI unit of electrical potential difference?", "back": "Volt (V)." },
  { "id": "fc_ssc_019", "front": "What is the pH value of a neutral solution?", "back": "7. Values below 7 are acidic, above 7 are basic." },
  { "id": "fc_ssc_020", "front": "What is the chemical formula of quicklime?", "back": "CaO (calcium oxide)." },
  { "id": "fc_ssc_021", "front": "What is the atomic number of Carbon?", "back": "6 (indicating 6 protons in its nucleus)." },
  { "id": "fc_ssc_022", "front": "What is the chemical formula of water?", "back": "H₂O." },
  { "id": "fc_ssc_023", "front": "Through which medium does sound travel fastest?", "back": "Solids, because particles are closely packed." },
  { "id": "fc_ssc_024", "front": "What does DNA stand for?", "back": "Deoxyribonucleic Acid." },
  { "id": "fc_ssc_025", "front": "What is sublimation?", "back": "The direct transition of a substance from solid to gas without passing through liquid (e.g., dry ice)." },
  { "id": "fc_ssc_026", "front": "Which vitamin is produced when skin is exposed to sunlight?", "back": "Vitamin D." },
  { "id": "fc_ssc_027", "front": "What does acid do to blue litmus paper?", "back": "Turns it red. Bases turn red litmus paper blue." },
  { "id": "fc_ssc_028", "front": "How many chambers does the human heart have?", "back": "4 chambers (two atria and two ventricles)." },
  { "id": "fc_ssc_029", "front": "What is the speed of light in vacuum?", "back": "Approximately 3 × 10⁸ m/s." },
  { "id": "fc_ssc_030", "front": "Which organ secretes the hormone insulin?", "back": "Pancreas." },
  { "id": "fc_ssc_031", "front": "What tissue transports water and minerals in plants?", "back": "Xylem tissue. Phloem transports food." },
  { "id": "fc_ssc_032", "front": "Who is known as the Father of Genetics?", "back": "Gregor Mendel." },
  { "id": "fc_ssc_033", "front": "What is transpiration?", "back": "The process of loss of water vapor from aerial parts (leaves) of a plant." },
  { "id": "fc_ssc_034", "front": "What is the chemical symbol for Gold?", "back": "Au (from Latin Aurum)." },
  { "id": "fc_ssc_035", "front": "Define power of a lens.", "back": "The reciprocal of its focal length in meters: P = 1/f. Measured in Dioptres (D)." },
  { "id": "fc_ssc_036", "front": "What gas is released during photosynthesis?", "back": "Oxygen (O₂)." },
  { "id": "fc_ssc_037", "front": "What is the SI unit of force?", "back": "Newton (N)." },
  { "id": "fc_ssc_038", "front": "Which mirror is used by dentists to view teeth?", "back": "Concave mirror (provides magnified virtual images)." },
  { "id": "fc_ssc_039", "front": "What is the primary ore of aluminum?", "back": "Bauxite." },
  { "id": "fc_ssc_040", "front": "What is the valence number of carbon?", "back": "4 (tetravalent)." },
  { "id": "fc_ssc_041", "front": "Define galvanization.", "back": "Coating iron with a thin protective layer of zinc to prevent rusting." },
  { "id": "fc_ssc_042", "front": "Which gas is majorly responsible for the greenhouse effect?", "back": "Carbon dioxide (CO₂)." },
  { "id": "fc_ssc_043", "front": "What basic unit makes up human kidneys?", "back": "Nephron." },
  { "id": "fc_ssc_044", "front": "What mode of asexual reproduction does Hydra use?", "back": "Budding." },
  { "id": "fc_ssc_045", "front": "What is the flow direction of energy in a food chain?", "back": "Unidirectional (moves up trophic levels, never reverses)." },
  { "id": "fc_ssc_046", "front": "Who was the first Prime Minister of independent India?", "back": "Jawaharlal Nehru." },
  { "id": "fc_ssc_047", "front": "When was the Indian Constitution adopted?", "back": "26 November 1949. It came into effect on 26 January 1950." },
  { "id": "fc_ssc_048", "front": "Which is the longest river in India?", "back": "Ganga (approximately 2,525 km)." },
  { "id": "fc_ssc_049", "front": "Who founded the Mughal Empire in India?", "back": "Babur, in 1526, after the First Battle of Panipat." },
  { "id": "fc_ssc_050", "front": "When was the Quit India Movement launched?", "back": "8 August 1942, by Mahatma Gandhi." },
  { "id": "fc_ssc_051", "front": "What does GDP stand for?", "back": "Gross Domestic Product." },
  { "id": "fc_ssc_052", "front": "When was the Reserve Bank of India established?", "back": "1 April 1935." },
  { "id": "fc_ssc_053", "front": "Which is the largest ocean in the world?", "back": "Pacific Ocean." },
  { "id": "fc_ssc_054", "front": "When did the French Revolution start?", "back": "1789, with the storming of the Bastille on July 14." },
  { "id": "fc_ssc_055", "front": "What does WTO stand for?", "back": "World Trade Organization." },
  { "id": "fc_ssc_056", "front": "Which line of latitude passes through India?", "back": "Tropic of Cancer (23.5° N)." },
  { "id": "fc_ssc_057", "front": "What is the highest peak in India?", "back": "Kanchenjunga." },
  { "id": "fc_ssc_058", "front": "Which river is called Dakshin Ganga?", "back": "Godavari." },
  { "id": "fc_ssc_059", "front": "What type of climate does India have?", "back": "Tropical Monsoon." },
  { "id": "fc_ssc_060", "front": "Where does the Indian Standard Time meridian pass through?", "back": "Mirzapur, near Allahabad in Uttar Pradesh (82.5° E)." },
  { "id": "fc_ssc_061", "front": "Which soil is best suited for growing cotton?", "back": "Black soil (also called Regur soil)." },
  { "id": "fc_ssc_062", "front": "Which movement was started in 1973 to save trees in Uttarakhand?", "back": "Chipko Movement." },
  { "id": "fc_ssc_063", "front": "Who was the head of the Drafting Committee of the Indian Constitution?", "back": "Dr. B.R. Ambedkar." },
  { "id": "fc_ssc_064", "front": "What sector does banking belong to?", "back": "Tertiary (or Service) sector." },
  { "id": "fc_ssc_065", "front": "When was the Right to Information (RTI) Act passed?", "back": "2005." },
  { "id": "fc_ssc_066", "front": "Who was the first President of independent India?", "back": "Dr. Rajendra Prasad." },
  { "id": "fc_ssc_067", "front": "What is the capital of India?", "back": "New Delhi." },
  { "id": "fc_ssc_068", "front": "What is the currency of India?", "back": "Indian Rupee (INR)." },
  { "id": "fc_ssc_069", "front": "Which planet is known as the Red Planet?", "back": "Mars." },
  { "id": "fc_ssc_070", "front": "What is an adverb?", "back": "A word that modifies a verb, adjective, or another adverb (e.g., quickly)." },
  { "id": "fc_ssc_071", "front": "Give a synonym of 'Benevolent'.", "back": "Kind." },
  { "id": "fc_ssc_072", "front": "What is the antonym of 'Optimistic'?", "back": "Pessimistic." },
  { "id": "fc_ssc_073", "front": "Define alliteration.", "back": "The repetition of the same consonant sound at the beginning of adjacent words." },
  { "id": "fc_ssc_074", "front": "What script is Hindi written in?", "back": "Devanagari script." },
  { "id": "fc_ssc_075", "front": "Who wrote 'Vande Mataram'?", "back": "Bankim Chandra Chattopadhyay." },
  { "id": "fc_ssc_076", "front": "Who wrote 'Jana Gana Mana'?", "back": "Rabindranath Tagore." },
  { "id": "fc_ssc_077", "front": "What is the new year festival of Andhra/Telangana called?", "back": "Ugadi." },
  { "id": "fc_ssc_078", "front": "Who wrote Telugu Mahabharatam?", "back": "Kavitrayam (Nannayya, Tikkanna, Errana)." },
  { "id": "fc_ssc_079", "front": "What are vowels called in Hindi?", "back": "Swar (स्वर)." },
  { "id": "fc_ssc_080", "front": "What is 'Prakriti' in English?", "back": "Nature." },
  { "id": "fc_ssc_081", "front": "How many letters are there in the English alphabet?", "back": "26 letters (5 vowels, 21 consonants)." },
  { "id": "fc_ssc_082", "front": "What is a collective noun?", "back": "A word naming a group of people or things (e.g., herd, team)." },
  { "id": "fc_ssc_083", "front": "What is the plural of child?", "back": "Children." },
  { "id": "fc_ssc_084", "front": "Define autobiography.", "back": "The story of a person's life written by that person." },
  { "id": "fc_ssc_085", "front": "What is the idiom 'crying over spilt milk'?", "back": "Regretting past actions that cannot be undone." },
  { "id": "fc_ssc_086", "front": "What punctuation marks show possession?", "back": "Apostrophe (e.g., John's book)." },
  { "id": "fc_ssc_087", "front": "Which script is Telugu written in?", "back": "Telugu script (derived from Brahmi script)." },
  { "id": "fc_ssc_088", "front": "In Telugu grammar, what is 'Achulu'?", "back": "Vowels (అ నుండి ఔ వరకు)." },
  { "id": "fc_ssc_089", "front": "In Telugu grammar, what is 'Hallulu'?", "back": "Consonants (క నుండి హ వరకు)." },
  { "id": "fc_ssc_090", "front": "Who wrote 'Godan'?", "back": "Munshi Premchand." },
  { "id": "fc_ssc_091", "front": "What is the largest continent by area?", "back": "Asia." },
  { "id": "fc_ssc_092", "front": "Define sustainable development.", "back": "Development that meets present needs without compromising future generations." },
  { "id": "fc_ssc_093", "front": "What sector does agriculture belong to?", "back": "Primary sector." },
  { "id": "fc_ssc_094", "front": "Name the 3 branches of Indian Government.", "back": "Executive, Legislature, and Judiciary." },
  { "id": "fc_ssc_095", "front": "What are the Directive Principles of State Policy?", "back": "Guidelines in Part IV of Constitution for establishing a welfare state." },
  { "id": "fc_ssc_096", "front": "What is the value of sin 30° + cos 60°?", "back": "1. (1/2 + 1/2 = 1)." },
  { "id": "fc_ssc_097", "front": "What is the discriminant of quadratic equation ax² + bx + c = 0?", "back": "b² - 4ac." },
  { "id": "fc_ssc_098", "front": "What is the LCM of 4, 6, and 12?", "back": "12." },
  { "id": "fc_ssc_099", "front": "What is the chemical formula of quicklime?", "back": "CaO." },
  { "id": "fc_ssc_100", "front": "Name the largest organ in the human body.", "back": "Skin." }
]
